{
	"id":"1",
	"title":"เซต",
	"topics":["เซตเบื้องต้น","วิธีการเขียนเซต","เอกภพสัมพัทธ์","เซตจำกัดและเซตอนัน","การเท่ากันของเซต"],
	"classrooms":["MHM0041"],
	"code":"XTZ5218",
	"duration": 0,
	"image":"set-logo.jpg",
	"username":"fscismi",
	"teacher_name":"ธเนษฐ ชวาลสันตติ",
	"subject":"คณิตศาสตร์",
	"degree":"ง่าย",
	"sections":[
		{
			"name":"บทเรียน",
			"contents":
			[
				{
					"id":"01",
					"title":"แนะนำเซต",
					"course_id":"1",
					"course_code":"XTZ5218",
					"duration":"",
					"type":"video",
					"slide":"",
					"logo":"fa-film",
					"content_url":"01.mp4",
					"not_start":["tonyball","chanon"],
					"started":[],
					"complete":["chanon","chatinya","chirapatr","chutipa","itouchz","jareewan","kantaporn","keeranat","kritawat","kritsada","kunlapat","natdecha","natthanon","thanwarat"],
					"remark":"",
					"number_of_question":"",
					"answer_of_question":[]

				},
				{
					"id":"02",
					"title":"ตัวอย่างที่ 1 ",
					"course_id":"1",
					"course_code":"XTZ5218",
					"duration":"",
					"content_url":"1.png",
					"type":"practice",
					"extended_remark":"",
					"answer_type":"tfq",
					"caption":["เกิดเซต","ไม่เกิดเซต"],
					"logo":"fa-pencil-square-o",
					"not_start":["tonyball","chanon","chatinya","chirapatr","chutipa","itouchz","jareewan","kantaporn","keeranat","kritawat","kritsada","kunlapat","natdecha","natthanon","thanwarat"],
					"started":[],
					"complete":[],
					"remark":"เลือกคำตอบว่า เกิดเซต หรือ ไม่เกิดเซต",
					"number_of_question":8,
					"answer_of_question":["เกิดเซต","เกิดเซต","เกิดเซต","ไม่เกิดเซต","เกิดเซต","เกิดเซต","ไม่เกิดเซต","เกิดเซต"]
				},
				{
					"id":"03",
					"title":"เฉลย ตัวอย่างที่ 1 ",
					"course_id":"1",
					"course_code":"XTZ5218",
					"duration":"",
					"logo":"fa-film",
					"content_url":"02.mp4",
					"type":"video",
					"slide":"",
					"logo":"fa-film",
					"not_start":["tonyball"],
					"started":["chanon","chatinya","chirapatr","chutipa","itouchz","jareewan","kantaporn","keeranat","kritawat","kritsada","kunlapat","natdecha","natthanon","thanwarat"],
					"complete":[],
					"remark":"",
					"number_of_question":"",
					"answer_of_question":[]
				},
				{
					"id":"04",
					"title":"วีธีการเขียนเซต",
					"course_id":"1",
					"course_code":"XTZ5218",
					"duration":"",
					"type":"video",
					"slide":"",
					"logo":"fa-film",
					"content_url":"03.mp4",
					"not_start":["tonyball"],
					"started":[],
					"complete":["chanon","chatinya","chirapatr","chutipa","itouchz","jareewan","kantaporn","keeranat","kritawat","kritsada","kunlapat","natdecha","natthanon","thanwarat"],
					"remark":"",
					"number_of_question":"",
					"answer_of_question":[]
				},
				{
					"id":"05",
					"title":"ตัวอย่างที่ 2 ",
					"course_id":"1",
					"course_code":"XTZ5218",
					"duration":"",
					"content_url":"2.png",
					"type":"practice",
					"extended_remark":"",
					"answer_type":"text",
					"caption":"",
					"logo":"fa-pencil-square-o",
					"not_start":["tonyball"],
					"started":[],
					"complete":[],
					"remark":"ให้อยู่ในรูปแบบ {a,b,c,...,z} ถ้าเป็น∅ให้พิมพ์ {∅}",
					"number_of_question":7,
					"answer_of_question":["{จันทบุรี}","{a,e,i,o,u}","{10,11,12,...,99}","{2,4,6,8}","{101,102,103,...}","{4,5,6,7,8,9}","{∅}"]
				},
				{
					"id":"06",
					"title":"เฉลย ตัวอย่างที่ 2",
					"course_id":"1",
					"course_code":"XTZ5218",
					"duration":"",
					"type":"video",
					"slide":"",
					"logo":"fa-film",
					"content_url":"04.mp4",
					"not_start":["tonyball"],
					"started":[],
					"complete":[],
					"remark":"",
					"number_of_question":"",
					"answer_of_question":[]
				},
				{
					"id":"07",
					"title":"ตัวอย่างที่ 3 ",
					"course_id":"1",
					"course_code":"XTZ5218",
					"duration":"",
					"content_url":"3.png",
					"type":"practice",
					"extended_remark":"",
					"answer_type":"text",
					"caption":"",
					"logo":"fa-pencil-square-o",
					"not_start":["tonyball"],
					"started":[],
					"complete":[],
					"remark":"ให้รู้ในรูปแบบ {x|x เงื่อนไข} ถ้าเป็นยกกำลังให้เขียนเป็น n^2 หน้าหลังเท่ากับให้เว้นวรรคด้วย",
					"number_of_question":4,
					"answer_of_question":["{x|x เป็นจำนวนคี่บวกและไม่เกินห้า}","{x|x เป็นจำนวนจริง}","{x|x= n^2n=จำนวนเต็มบวก}","{x|x = 10nเมื่อnเป็นจำนวนเต็มบวก}"]
				},
				{
					"id":"08",
					"title":"เฉลย ตัวอย่างที่ 3 ",
					"course_id":"1",
					"course_code":"XTZ5218",
					"duration":"",
					"type":"video",
					"slide":"",
					"logo":"fa-film",
					"content_url":"05.mp4",
					"not_start":["tonyball"],
					"started":[],
					"complete":[],
					"remark":"",
					"number_of_question":"",
					"answer_of_question":[]
				},
				{
					"id":"09",
					"title":"เอกภพสัมพัทธ์",
					"course_id":"1",
					"course_code":"XTZ5218",
					"duration":"",	
					"type":"video",
					"slide":"",
					"logo":"fa-film",
					"content_url":"06.mp4",
					"not_start":["tonyball"],
					"started":[],
					"complete":[],
					"remark":"",
					"number_of_question":"",
					"answer_of_question":[]
				},
				{
					"id":"10",
					"title":"เซตจำกัดและเซตอนันต์",
					"course_id":"1",
					"course_code":"XTZ5218",
					"duration":"",
					"type":"video",
					"slide":"",
					"logo":"fa-film",
					"content_url":"07.mp4",
					"not_start":["tonyball"],
					"started":[],
					"complete":[],
					"remark":"",
					"number_of_question":"",
					"answer_of_question":[]
				},
				{
					"id":"11",
					"title":"ตัวอย่างที่ 4 ",
					"course_id":"1",
					"course_code":"XTZ5218",
					"duration":"",
					"content_url":"4.png",
					"type":"practice",
					"extended_remark":"",
					"answer_type":"tfq",
					"caption":["เซตจำกัด","เซตอนันต์"],
					"logo":"fa-pencil-square-o",
					"not_start":["tonyball"],
					"started":[],
					"complete":[],
					"remark":"ให้ตอบเป็น เซตจำกัด หรือ เซตอนันต์",
					"number_of_question":7,
					"answer_of_question":["เซตอนันต์","เซตจำกัด","เซตอนันต์","เซตจำกัด","เซตอนันต์","เซตจำกัด","เซตจำกัด"]
				},
				{
					"id":"12",
					"title":"เฉลย ตัวอย่างที่ 4",
					"course_id":"1",
					"course_code":"XTZ5218",
					"duration":"",
					"type":"video",
					"slide":"",
					"logo":"fa-film",
					"content_url":"08.mp4",
					"not_start":["tonyball"],
					"started":[],
					"complete":[],
					"remark":"",
					"number_of_question":"",
					"answer_of_question":[]
				},
				{
					"id":"13",
					"title":"ตัวอย่างที่ 5 ",
					"course_id":"1",
					"course_code":"XTZ5218",
					"duration":"",
					"content_url":"5.png",
					"type":"practice",
					"extended_remark":"",
					"answer_type":"text",
					"caption":"",
					"logo":"fa-pencil-square-o",
					"not_start":["tonyball"],
					"started":[],
					"complete":[],
					"remark":"ให้ตอบเป็นตัวเลข",
					"number_of_question":4,
					"answer_of_question":["1","7","0","4"]
				},
				{
					"id":"14",
					"title":"เฉลย ตัวอย่างที่ 5",
					"course_id":"1",
					"course_code":"XTZ5218",
					"duration":"",
					"type":"video",
					"slide":"",
					"logo":"fa-film",
					"content_url":"09.mp4",
					"not_start":["tonyball"],
					"started":[],
					"complete":[],
					"remark":"",
					"number_of_question":"",
					"answer_of_question":[]
				},
				{
					"id":"15",
					"title":"การเท่ากันของเซต",
					"course_id":"1",
					"course_code":"XTZ5218",
					"duration":"",
					"type":"video",
					"slide":"",
					"logo":"fa-film",
					"content_url":"10.mp4",
					"not_start":["tonyball"],
					"started":[],
					"complete":[],
					"remark":"",
					"number_of_question":"",
					"answer_of_question":[]
				},
				{
					"id":"16",
					"title":"การเท่ากันของเซต 2",
					"course_id":"1",
					"course_code":"XTZ5218",
					"duration":"",
					"type":"video",
					"slide":"",
					"logo":"fa-film",
					"content_url":"11.mp4",
					"not_start":["tonyball"],
					"started":[],
					"complete":[],
					"remark":"",
					"number_of_question":"",
					"answer_of_question":[]
				},
				{
					"id":"17",
					"title":"ตัวอย่างที่ 7 ",
					"course_id":"1",
					"course_code":"XTZ5218",
					"duration":"",
					"content_url":"6.png",
					"type":"practice",
					"extended_remark":"",
					"answer_type":"tfq",
					"caption":["เท่ากัน","ไม่เท่ากัน"],
					"logo":"fa-pencil-square-o",
					"not_start":["tonyball"],
					"started":[],
					"complete":[],
					"remark":"ให้ตอบว่าเท่ากันหรือไม่เท่ากัน",
					"number_of_question":3,
					"answer_of_question":["ไม่เท่ากัน","เท่ากัน","เท่ากัน"]
				},
				{
					"id":"18",
					"title":"เฉลย ตัวอย่างที่ 7",
					"course_id":"1",
					"course_code":"XTZ5218",
					"duration":"",
					"type":"video",
					"slide":"",
					"logo":"fa-film",
					"content_url":"12.mp4",
					"not_start":["tonyball"],
					"started":[],
					"complete":[],
					"remark":"",
					"number_of_question":"",
					"answer_of_question":[]
				},
				{
					"id":"19",
					"title":"การเทียบเท่ากันของเซต",
					"course_id":"1",
					"course_code":"XTZ5218",
					"duration":"",
					"type":"video",
					"slide":"",
					"logo":"fa-film",
					"content_url":"13.mp4",
					"not_start":["tonyball"],
					"started":[],
					"complete":[],
					"remark":"",
					"number_of_question":"",
					"answer_of_question":[]
				},
				{
					"id":"20",
					"title":"ตัวอย่างที่ 8 ",
					"course_id":"1",
					"course_code":"XTZ5218",
					"duration":"",
					"content_url":"7.png",
					"type":"practice",
					"extended_remark":"",
					"answer_type":"tfq",
					"caption":["ถูก","ผิด"],
					"logo":"fa-pencil-square-o",
					"not_start":["tonyball"],
					"started":[],
					"complete":[],
					"remark":"ให้ตอบถูกหรือผิด",
					"number_of_question":10,
					"answer_of_question":["ถูก","ผิด","ผิด","ถูก","ถูก","ผิด","ผิด","ถูก","ผิด","ถูก"]
				},
				{
					"id":"21",
					"title":"เฉลย ตัวอย่างที่ 8",
					"course_id":"1",
					"course_code":"XTZ5218",
					"duration":"",
					"type":"video",
					"slide":"",
					"logo":"fa-film",
					"content_url":"14.mp4",
					"not_start":["tonyball"],
					"started":[],
					"complete":[],
					"remark":"",
					"number_of_question":"",
					"answer_of_question":[]
				},
				{
					"id":"22",
					"title":"สับเซต",
					"course_id":"1",
					"course_code":"XTZ5218",
					"duration":"",
					"type":"video",
					"slide":"",
					"logo":"fa-film",
					"content_url":"15.mp4",
					"not_start":["tonyball"],
					"started":[],
					"complete":[],
					"remark":"",
					"number_of_question":"",
					"answer_of_question":[]
				},
				{
					"id":"23",
					"title":"ตัวอย่างที่ 9 ",
					"course_id":"1",
					"course_code":"XTZ5218",
					"duration":"",
					"content_url":"8.png",
					"type":"practice",
					"extended_remark":"",
					"answer_type":"tfq",
					"caption":["A เป็นสับเซต B","A ไม่เป็นสับเซต B"],
					"logo":"fa-pencil-square-o",
					"not_start":["tonyball"],
					"started":[],
					"complete":[],
					"remark":"ให้ตอบว่า A เป็นสับเซต B หรือไม่",
					"number_of_question":2,
					"answer_of_question":["A เป็นสับเซต B","A ไม่เป็นสับเซต B"]
				},
				{
					"id":"24",
					"title":"เฉลย ตัวอย่างที่ 9",
					"course_id":"1",
					"course_code":"XTZ5218",
					"duration":"",
					"type":"video",
					"slide":"",
					"logo":"fa-film",
					"content_url":"16.mp4",
					"not_start":["tonyball"],
					"started":[],
					"complete":[],
					"remark":"",
					"number_of_question":"",
					"answer_of_question":[]
				},
				{
					"id":"25",
					"title":"ข้อสังเกตสับเซต",
					"course_id":"1",
					"course_code":"XTZ5218",
					"duration":"",
					"type":"video",
					"slide":"",
					"logo":"fa-film",
					"content_url":"17.mp4",
					"not_start":["tonyball"],
					"started":[],
					"complete":[],
					"remark":"",
					"number_of_question":"",
					"answer_of_question":[]
				},
				{
					"id":"26",
					"title":"ตัวอย่างที่ 10 ",
					"course_id":"1",
					"course_code":"XTZ5218",
					"duration":"",
					"content_url":"9.png",
					"type":"practice",
					"extended_remark":"",
					"answer_type":"multiple",
					"caption":["1","2","3","4"],
					"logo":"fa-pencil-square-o",
					"not_start":["tonyball"],
					"started":[],
					"complete":[],
					"remark":"ให้เลือกข้อที่ถูกต้องที่สุด",
					"number_of_question":1,
					"answer_of_question":["4"]
				},
				{
					"id":"27",
					"title":"เฉลย ตัวอย่างที่ 10",
					"course_id":"1",
					"course_code":"XTZ5218",
					"duration":"",
					"type":"video",
					"slide":"",
					"logo":"fa-film",
					"content_url":"18.mp4",
					"not_start":["tonyball"],
					"started":[],
					"complete":[],
					"remark":"",
					"number_of_question":"",
					"answer_of_question":[]
				},
				{
					"id":"28",
					"title":"ตัวอย่างที่ 11 ",
					"course_id":"1",
					"course_code":"XTZ5218",
					"duration":"",
					"content_url":"10.png",
					"type":"practice",
					"extended_remark":"",
					"answer_type":"tfq",
					"caption":["ถูก","ผิด"],
					"logo":"fa-pencil-square-o",
					"not_start":["tonyball"],
					"started":[],
					"complete":[],
					"remark":"ให้ตอบว่าถูกหรือผิด",
					"number_of_question":11,
					"answer_of_question":["ผิด","ถูก","ถูก","ผิด","ถูก","ถูก","ถูก","ถูก","ถูก","ผิด","ถูก"]
				},
				{
					"id":"29",
					"title":"เฉลย ตัวอย่างที่ 11",
					"course_id":"1",
					"course_code":"XTZ5218",
					"duration":"",
					"type":"video",
					"slide":"",
					"logo":"fa-film",
					"content_url":"19.mp4",
					"not_start":["tonyball"],
					"started":[],
					"complete":[],
					"remark":"",
					"number_of_question":"",
					"answer_of_question":[]
				},
				{
					"id":"30",
					"title":"ตัวอย่างที่ 12 ",
					"course_id":"1",
					"course_code":"XTZ5218",
					"duration":"",
					"content_url":"11.png",
					"type":"practice",
					"extended_remark":"",
					"answer_type":"multiple",
					"caption":["1","2","3","4"],
					"logo":"fa-pencil-square-o",
					"not_start":["tonyball"],
					"started":[],
					"complete":[],
					"remark":"ให้ตอบเป็นตัวเลข",
					"number_of_question":1,
					"answer_of_question":["2"]
				},
				{
					"id":"31",
					"title":"เฉลย ตัวอย่างที่ 12",
					"course_id":"1",
					"course_code":"XTZ5218",
					"duration":"",
					"type":"video",
					"slide":"",
					"logo":"fa-film",
					"content_url":"20.mp4",
					"not_start":["tonyball"],
					"started":[],
					"complete":[],
					"remark":"",
					"number_of_question":"",
					"answer_of_question":[]
				},
				{
					"id":"32",
					"title":"ตัวอย่างที่ 13 ",
					"course_id":"1",
					"course_code":"XTZ5218",
					"duration":"",
					"content_url":"12.png",
					"type":"practice",
					"extended_remark":["สับเซต","จำนวนสับเซต","จำนวนสับเซตแท้"],
					"answer_type":"multitext",
					"caption":"",
					"logo":"fa-pencil-square-o",
					"not_start":["tonyball"],
					"started":[],
					"complete":[],
					"remark":"ให้ตอบคำถามต่อไปนี้ ตามที่กำหนด",
					"number_of_question":4,
					"answer_of_question":["{∅} 1 0","{∅,1} 2 1","{∅,{1},{2},{1,2}} 4 3","{∅,{1},{2},{3},{1,2},{1,3},{2,3},{1,2,3}} 8 7"]
				},
				{
					"id":"33",
					"title":"เฉลย ตัวอย่างที่ 13",
					"course_id":"1",
					"course_code":"XTZ5218",
					"duration":"",
					"type":"video",
					"slide":"",
					"logo":"fa-film",
					"content_url":"21.mp4",
					"not_start":["tonyball"],
					"started":[],
					"complete":[],
					"remark":"",
					"number_of_question":"",
					"answer_of_question":[]
				},
				{
					"id":"34",
					"title":"คุณสมบัติของสับเซต",
					"course_id":"1",
					"course_code":"XTZ5218",
					"duration":"",
					"type":"video",
					"slide":"",
					"logo":"fa-film",
					"content_url":"22.mp4",
					"not_start":["tonyball"],
					"started":[],
					"complete":[],
					"remark":"",
					"number_of_question":"",
					"answer_of_question":[]
				},
				{
					"id":"35",
					"title":"ตัวอย่างที่ 14 ",
					"course_id":"1",
					"course_code":"XTZ5218",
					"duration":"",
					"content_url":"13.png",
					"type":"practice",
					"extended_remark":"",
					"answer_type":"multiple",
					"caption":["1","2","3","4"],
					"logo":"fa-pencil-square-o",
					"not_start":["tonyball"],
					"started":[],
					"complete":[],
					"remark":"ให้ตอบเป็นตัวเลข",
					"number_of_question":1,
					"answer_of_question":["3"]
				},
				{
					"id":"36",
					"title":"เฉลย ตัวอย่างที่ 14",
					"course_id":"1",
					"course_code":"XTZ5218",
					"duration":"",
					"type":"video",
					"slide":"",
					"logo":"fa-film",
					"content_url":"23.mp4",
					"not_start":["tonyball"],
					"started":[],
					"complete":[],
					"remark":"",
					"number_of_question":"",
					"answer_of_question":[]
				},
				{
					"id":"37",
					"title":"พาวเวอร์เซต",
					"course_id":"1",
					"course_code":"XTZ5218",
					"duration":"",
					"type":"video",
					"slide":"",
					"logo":"fa-film",
					"content_url":"24.mp4",
					"not_start":["tonyball"],
					"started":[],
					"complete":[],
					"remark":"",
					"number_of_question":"",
					"answer_of_question":[]
				},
				{
					"id":"38",
					"title":"ตัวอย่างที่ 15",
					"course_id":"1",
					"course_code":"XTZ5218",
					"duration":"",
					"content_url":"14.png",
					"type":"practice",
					"extended_remark":["พาวเวอร์เซต","จำนวนของพาวเวอร์เซต"],
					"answer_type":"multitext",
					"caption":"",
					"logo":"fa-pencil-square-o",
					"not_start":["tonyball"],
					"started":[],
					"complete":[],
					"remark":"ให้ตอบเป็นตัวเลข",
					"number_of_question":3,
					"answer_of_question":["{∅,{a},{b},{a,b}} 4","{∅,{1},{2},{3},{1,2},{1,3},{2,3},{1,2,3}} 8","{∅} 1"]
				},
				{
					"id":"39",
					"title":"เฉลย ตัวอย่างที่ 15",
					"course_id":"1",
					"course_code":"XTZ5218",
					"duration":"",
					"type":"video",
					"slide":"",
					"logo":"fa-film",
					"content_url":"25.mp4",
					"not_start":["tonyball"],
					"started":[],
					"complete":[],
					"remark":"",
					"number_of_question":"",
					"answer_of_question":[]
				},
				{
					"id":"40",
					"title":"คุณสมบัติของพาวเวอร์เซต 1",
					"course_id":"1",
					"course_code":"XTZ5218",
					"duration":"",
					"type":"video",
					"slide":"",
					"logo":"fa-film",
					"content_url":"26.mp4",
					"not_start":["tonyball"],
					"started":[],
					"complete":[],
					"remark":"",
					"number_of_question":"",
					"answer_of_question":[]
				},
				{
					"id":"41",
					"title":"คุณสมบัติของพาวเวอร์เซต 2",
					"course_id":"1",
					"course_code":"XTZ5218",
					"duration":"",
					"type":"video",
					"slide":"",
					"logo":"fa-film",
					"content_url":"27.mp4",
					"not_start":["tonyball"],
					"started":[],
					"complete":[],
					"remark":"",
					"number_of_question":"",
					"answer_of_question":[]
				},
				{
					"id":"42",
					"title":"ตัวอย่างที่ 16 ",
					"course_id":"1",
					"course_code":"XTZ5218",
					"duration":"",
					"content_url":"15.png",
					"type":"practice",
					"extended_remark":"",
					"answer_type":"tfq",
					"caption":["ถูก","ผิด"],
					"logo":"fa-pencil-square-o",
					"not_start":["tonyball"],
					"started":[],
					"complete":[],
					"remark":"ให้ตอบว่าถูกหรือผิด",
					"number_of_question":10,
					"answer_of_question":["ถูก","ถูก","ถูก","ถูก","ผิด","ถูก","ถูก","ผิด","ถูก","ถูก"]
				},
				{
					"id":"42",
					"title":"เฉลย ตัวอย่างที่ 16",
					"course_id":"1",
					"course_code":"XTZ5218",
					"duration":"",
					"type":"video",
					"slide":"",
					"logo":"fa-film",
					"content_url":"28.mp4",
					"not_start":["tonyball"],
					"started":[],
					"complete":[],
					"remark":"",
					"number_of_question":"",
					"answer_of_question":[]
				},
				{
					"id":"43",
					"title":"ตัวอย่างที่ 17 ",
					"course_id":"1",
					"course_code":"XTZ5218",
					"duration":"",
					"content_url":"16.png",
					"type":"practice",
					"extended_remark":"",
					"answer_type":"multiple",
					"caption":["1","2","3","4"],
					"logo":"fa-pencil-square-o",
					"not_start":["tonyball"],
					"started":[],
					"complete":[],
					"remark":"ให้เลือกข้อที่ถูกต้องที่สุด",
					"number_of_question":1,
					"answer_of_question":["4"]
				},
				{
					"id":"44",
					"title":"เฉลย ตัวอย่างที่ 17",
					"course_id":"1",
					"course_code":"XTZ5218",
					"duration":"",
					"type":"video",
					"slide":"",
					"logo":"fa-film",
					"content_url":"29.mp4",
					"not_start":["tonyball"],
					"started":[],
					"complete":[],
					"remark":"",
					"number_of_question":"",
					"answer_of_question":[]
				},
				{
					"id":"45",
					"title":"ตัวอย่างที่ 19 ",
					"course_id":"1",
					"course_code":"XTZ5218",
					"duration":"",
					"content_url":"17.png",
					"type":"practice",
					"extended_remark":"",
					"answer_type":"multiple",
					"caption":["1","2","3","4"],
					"logo":"fa-pencil-square-o",
					"not_start":["tonyball"],
					"started":[],
					"complete":[],
					"remark":"ให้เลือกข้อที่ถูกต้องที่สุด",
					"number_of_question":1,
					"answer_of_question":["1"]
				},
				{
					"id":"46",
					"title":"เฉลย ตัวอย่างที่ 19",
					"course_id":"1",
					"course_code":"XTZ5218",
					"duration":"",
					"type":"video",
					"slide":"",
					"logo":"fa-film",
					"content_url":"30.mp4",
					"not_start":["tonyball"],
					"started":[],
					"complete":[],
					"remark":"",
					"number_of_question":"",
					"answer_of_question":[]
				},
				{
					"id":"46x",
					"title":"แบบฝึกหัดที่ 1",
					"course_id":"1",
					"course_code":"XTZ5218",
					"duration":"",
					"content_url":"hw1.pdf",
					"type":"practice",
					"extended_remark":"",
					"answer_type":"multiple",
					"caption":["1","2","3","4"],
					"logo":"fa-pencil-square-o",
					"not_start":["tonyball"],
					"started":[],
					"complete":[],
					"remark":"จงเลือกข้อที่ถูกต้องที่สุด",
					"number_of_question":27,
					"answer_of_question":[1,2,3,1,4,4,4,3,1,3,2,3,2,2,2,3,3,1,2,2,1,3,4,4,3,3,4]
				},
				{
					"id":"47",
					"title":"แผนภาพ Venn-Euler",
					"course_id":"1",
					"course_code":"XTZ5218",
					"duration":"",
					"type":"video",
					"slide":"",
					"logo":"fa-film",
					"content_url":"31.mp4",
					"not_start":["tonyball"],
					"started":[],
					"complete":[],
					"remark":"",
					"number_of_question":"",
					"answer_of_question":[]
				},
				{
					"id":"48",
					"title":"การกระทำบนเซต",
					"course_id":"1",
					"course_code":"XTZ5218",
					"duration":"",
					"type":"video",
					"slide":"",
					"logo":"fa-film",
					"content_url":"32.mp4",
					"not_start":["tonyball"],
					"started":[],
					"complete":[],
					"remark":"",
					"number_of_question":"",
					"answer_of_question":[]
				},
				{
					"id":"49",
					"title":"ตัวอย่างที่ 20 ",
					"course_id":"1",
					"course_code":"XTZ5218",
					"duration":"",
					"content_url":"18.png",
					"type":"practice",
					"extended_remark":"",
					"answer_type":"text",
					"caption":"",
					"logo":"fa-pencil-square-o",
					"not_start":["tonyball"],
					"started":[],
					"complete":[],
					"remark":"ให้ตอบเป็นเซต",
					"number_of_question":8,
					"answer_of_question":["{1,2,3,4,5}","{3,4}","{1,2}","{1,2,6,7,8}","{7,8}","{6,7,8}","{∅}","{1,2,3,4,5,6,7,8}"]
				},
				{
					"id":"50",
					"title":"เฉลย ตัวอย่างที่ 20 ",
					"course_id":"1",
					"course_code":"XTZ5218",
					"duration":"",
					"type":"video",
					"slide":"",
					"logo":"fa-film",
					"content_url":"33.mp4",
					"not_start":["tonyball"],
					"started":[],
					"complete":[],
					"remark":"",
					"number_of_question":"",
					"answer_of_question":[]
				},
				{
					"id":"51",
					"title":"ตัวอย่างที่ 23 ",
					"course_id":"1",
					"course_code":"XTZ5218",
					"duration":"",
					"content_url":"19.png",
					"type":"practice",
					"extended_remark":"",
					"answer_type":"text",
					"caption":"",
					"logo":"fa-pencil-square-o",
					"not_start":["tonyball"],
					"started":[],
					"complete":[],
					"remark":"ให้วาดแผนภาพในกระดาษทด (เครื่องไม่ตรวจ)",
					"number_of_question":0,
					"answer_of_question":["1","7","0","4"]
				},
				{
					"id":"52",
					"title":"เฉลย ตัวอย่างที่ 23",
					"course_id":"1",
					"course_code":"XTZ5218",
					"duration":"",
					"type":"video",
					"slide":"",
					"logo":"fa-film",
					"content_url":"34.mp4",
					"not_start":["tonyball"],
					"started":[],
					"complete":[],
					"remark":"",
					"number_of_question":"",
					"answer_of_question":[]
				},
				{
					"id":"53",
					"title":"ตัวอย่างที่ 25 ",
					"course_id":"1",
					"course_code":"XTZ5218",
					"duration":"",
					"content_url":"20.png",
					"type":"practice",
					"extended_remark":"",
					"answer_type":"multiple",
					"caption":["1","2","3","4"],
					"logo":"fa-pencil-square-o",
					"not_start":["tonyball"],
					"started":[],
					"complete":[],
					"remark":"ให้เลือกข้อที่ถูกต้องที่สุด",
					"number_of_question":1,
					"answer_of_question":["2"]
				},
				{
					"id":"54",
					"title":"เฉลย ตัวอย่างที่ 25",
					"course_id":"1",
					"course_code":"XTZ5218",
					"duration":"",
					"type":"video",
					"slide":"",
					"logo":"fa-film",
					"content_url":"35.mp4",
					"not_start":["tonyball"],
					"started":[],
					"complete":[],
					"remark":"",
					"number_of_question":"",
					"answer_of_question":[]
				},
				{
					"id":"46y",
					"title":"แบบฝึกหัดที่ 2",
					"course_id":"1",
					"course_code":"XTZ5218",
					"duration":"",
					"content_url":"hw2.pdf",
					"type":"practice",
					"extended_remark":"",
					"answer_type":"multiple",
					"caption":["1","2","3","4"],
					"logo":"fa-pencil-square-o",
					"not_start":["tonyball"],
					"started":[],
					"complete":[],
					"remark":"จงเลือกข้อที่ถูกต้องที่สุด",
					"number_of_question":21,
					"answer_of_question":[4,2,4,3,3,3,8,2,1,1,4,1,1,4,2,33,2,3,3,3,4]
				},
				{
					"id":"55",
					"title":"คุณสมบัติการดำเนินการของเซต",
					"course_id":"1",
					"course_code":"XTZ5218",
					"duration":"",
					"type":"video",
					"slide":"",
					"logo":"fa-film",
					"content_url":"36.mp4",
					"not_start":["tonyball"],
					"started":[],
					"complete":[],
					"remark":"",
					"number_of_question":"",
					"answer_of_question":[]
				},
				{
					"id":"56",
					"title":"กฏการเท่ากันของเซต",
					"course_id":"1",
					"course_code":"XTZ5218",
					"duration":"",
					"type":"video",
					"slide":"",
					"logo":"fa-film",
					"content_url":"37.mp4",
					"not_start":["tonyball"],
					"started":[],
					"complete":[],
					"remark":"",
					"number_of_question":"",
					"answer_of_question":[]
				},
				{
					"id":"57",
					"title":"ตัวอย่างที่ 27 ",
					"course_id":"1",
					"course_code":"XTZ5218",
					"duration":"",
					"content_url":"21.png",
					"type":"practice",
					"extended_remark":"",
					"answer_type":"tfq",
					"caption":["ถูก","ผิด"],
					"logo":"fa-pencil-square-o",
					"not_start":["tonyball"],
					"started":[],
					"complete":[],
					"remark":"ให้ตอบว่าถูกหรือผิด",
					"number_of_question":2,
					"answer_of_question":["ถูก","ผิด"]
				},
				{
					"id":"58",
					"title":"เฉลย ตัวอย่างที่ 27",
					"course_id":"1",
					"course_code":"XTZ5218",
					"duration":"",
					"type":"video",
					"slide":"",
					"logo":"fa-film",
					"content_url":"38.mp4",
					"not_start":["tonyball"],
					"started":[],
					"complete":[],
					"remark":"",
					"number_of_question":"",
					"answer_of_question":[]
				},
				{
					"id":"59",
					"title":"ตัวอย่างที่ 30 ",
					"course_id":"1",
					"course_code":"XTZ5218",
					"duration":"",
					"content_url":"22.png",
					"type":"practice",
					"extended_remark":"",
					"answer_type":"multiple",
					"caption":["1","2","3","4"],
					"logo":"fa-pencil-square-o",
					"not_start":["tonyball"],
					"started":[],
					"complete":[],
					"remark":"ให้เลือกข้อที่ถูกต้องที่สุด",
					"number_of_question":1,
					"answer_of_question":["2"]
				},
				{
					"id":"60",
					"title":"เฉลย ตัวอย่างที่ 30",
					"course_id":"1",
					"course_code":"XTZ5218",
					"duration":"",
					"type":"video",
					"slide":"",
					"logo":"fa-film",
					"content_url":"39.mp4",
					"not_start":["tonyball"],
					"started":[],
					"complete":[],
					"remark":"",
					"number_of_question":"",
					"answer_of_question":[]
				},
				{
					"id":"46z",
					"title":"แบบฝึกหัดที่ 3",
					"course_id":"1",
					"course_code":"XTZ5218",
					"duration":"",
					"content_url":"hw3.pdf",
					"type":"practice",
					"extended_remark":"",
					"answer_type":"multiple",
					"caption":["1","2","3","4"],
					"logo":"fa-pencil-square-o",
					"not_start":["tonyball"],
					"started":[],
					"complete":[],
					"remark":"จงเลือกข้อที่ถูกต้องที่สุด",
					"number_of_question":19,
					"answer_of_question":[1,3,3,2,4,4,1,3,2,1,3,2,3,3,2,3,4,3,3]
				}
			]
		},
		{
			"name": "ทบทวน",
			"contents":
			[
				{
					"id":"61",
					"title":"แนะนำเซต",
					"course_id":"1",
					"course_code":"XTZ5218",
					"duration":"",
					"type":"video",
					"slide":"",
					"logo":"fa-film",
					"content_url":"1.mp4",
					"not_start":["tonyball"],
					"started":[],
					"complete":[],
					"remark":"",
					"number_of_question":"",
					"answer_of_question":[]
				},
				{
					"id":"62",
					"title":"โจทย์ที่ 1 ",
					"course_id":"1",
					"course_code":"XTZ5218",
					"duration":"",
					"content_url":"1.png",
					"type":"practice",
					"extended_remark":"",
					"answer_type":"multiple",
					"caption":["1","2","3","4"],
					"logo":"fa-pencil-square-o",
					"not_start":["tonyball"],
					"started":[],
					"complete":[],
					"remark":"เลือกข้อที่ถูกต้องที่สุด",
					"number_of_question":1,
					"answer_of_question":["1"]
				},
				{
					"id":"63",
					"title":"เฉลย โจทย์ที่ 1 ",
					"course_id":"1",
					"course_code":"XTZ5218",
					"duration":"",
					"type":"video",
					"slide":"",
					"logo":"fa-film",
					"content_url":"2.mp4",
					"not_start":["tonyball"],
					"started":[],
					"complete":[],
					"remark":"",
					"number_of_question":"",
					"answer_of_question":[]
				},
				{
					"id":"64",
					"title":"โจทยที่ 2",
					"course_id":"1",
					"course_code":"XTZ5218",
					"duration":"",
					"type":"practice",
					"extended_remark":"",
					"answer_type":"multiple",
					"caption":["1","2","3","4"],
					"logo":"fa-pencil-square-o",
					"content_url":"2.png",
					"not_start":["tonyball"],
					"started":[],
					"complete":[],
					"remark":"เลือกข้อที่ถูกต้องที่สุด",
					"number_of_question":1,
					"answer_of_question":["4"]
				},
				{
					"id":"65",
					"title":"เฉลย โจทย์ที่ 2 ",
					"course_id":"1",
					"course_code":"XTZ5218",
					"duration":"",
					"content_url":"3.mp4",
					"type":"video",
					"slide":"",
					"logo":"fa-film",
					"not_start":["tonyball"],
					"started":[],
					"complete":[],
					"remark":"",
					"number_of_question":"",
					"answer_of_question":[]
				},
				{
					"id":"66",
					"title":"โจทยที่ 3",
					"course_id":"1",
					"course_code":"XTZ5218",
					"duration":"",
					"type":"practice",
					"extended_remark":"",
					"answer_type":"multiple",
					"caption":["1","2","3","4"],
					"logo":"fa-pencil-square-o",
					"content_url":"3.png",
					"not_start":["tonyball"],
					"started":[],
					"complete":[],
					"remark":"ให้ตอบเป็นข้อ",
					"number_of_question":1,
					"answer_of_question":["3"]
				},
				{
					"id":"67",
					"title":"เฉลย โจทย์ที่ 3 ",
					"course_id":"1",
					"course_code":"XTZ5218",
					"duration":"",
					"content_url":"4.mp4",
					"type":"video",
					"slide":"",
					"logo":"fa-film",
					"not_start":["tonyball"],
					"started":[],
					"complete":[],
					"remark":"",
					"number_of_question":"",
					"answer_of_question":[]
				},
				{
					"id":"68",
					"title":"โจทยที่ 4",
					"course_id":"1",
					"course_code":"XTZ5218",
					"duration":"",
					"type":"practice",
					"extended_remark":"",
					"answer_type":"multiple",
					"caption":["1","2","3","4"],
					"logo":"fa-pencil-square-o",
					"content_url":"4.png",
					"not_start":["tonyball"],
					"started":[],
					"complete":[],
					"remark":"เลือกข้อที่ถูกต้องที่สุด",
					"number_of_question":1,
					"answer_of_question":["4"]
				},
				{
					"id":"69",
					"title":"เฉลย โจทย์ที่ 4 ",
					"course_id":"1",
					"course_code":"XTZ5218",
					"duration":"",
					"content_url":"5.mp4",
					"type":"video",
					"slide":"",
					"logo":"fa-film",
					"not_start":["tonyball"],
					"started":[],
					"complete":[],
					"remark":"",
					"number_of_question":"",
					"answer_of_question":[]
				},
				{
					"id":"70",
					"title":"ประเภทของเซต ",
					"course_id":"1",
					"course_code":"XTZ5218",
					"duration":"",
					"content_url":"6.mp4",
					"type":"video",
					"slide":"",
					"logo":"fa-film",
					"not_start":["tonyball"],
					"started":[],
					"complete":[],
					"remark":"",
					"number_of_question":"",
					"answer_of_question":[]
				},
				{
					"id":"71",
					"title":"โจทยที่ 5",
					"course_id":"1",
					"course_code":"XTZ5218",
					"duration":"",
					"type":"practice",
					"extended_remark":["จำนวนสมาชิกของเซต"],
					"answer_type":"tfqx",
					"caption":["เซตจำกัด","เซตอนันต์"],
					"logo":"fa-pencil-square-o",
					"content_url":"5.png",
					"not_start":["tonyball"],
					"started":[],
					"complete":[],
					"remark":"ให้ตอบเป็นจำนวนและบอกว่าเป็นเซตกำจัด หรือ เซตอนันต์",
					"number_of_question":8,
					"answer_of_question":["1 เซตจำกัด","3 เซตจำกัด","5 เซตจำกัด","- เซตอนันต์","4 เซตจำกัด","2 เซตจำกัด","0 เซตจำกัด","- เซตอนันต์"]
				},
				{
					"id":"72",
					"title":"เฉลย โจทย์ที่ 5 ",
					"course_id":"1",
					"course_code":"XTZ5218",
					"duration":"",
					"content_url":"7.mp4",
					"type":"video",
					"slide":"",
					"logo":"fa-film",
					"not_start":["tonyball"],
					"started":[],
					"complete":[],
					"remark":"",
					"number_of_question":"",
					"answer_of_question":[]
				},
				{
					"id":"73",
					"title":"โจทยที่ 6",
					"course_id":"1",
					"course_code":"XTZ5218",
					"duration":"",
					"type":"practice",
					"extended_remark":"",
					"answer_type":"multiple",
					"caption":["1","2","3","4"],
					"logo":"fa-pencil-square-o",
					"content_url":"6.png",
					"not_start":["tonyball"],
					"started":[],
					"complete":[],
					"remark":"เลือกข้อที่ถูกต้องที่สุด",
					"number_of_question":1,
					"answer_of_question":["4"]
				},
				{
					"id":"74",
					"title":"เฉลย โจทย์ที่ 6 ",
					"course_id":"1",
					"course_code":"XTZ5218",
					"duration":"",
					"content_url":"8.mp4",
					"type":"video",
					"slide":"",
					"logo":"fa-film",
					"not_start":["tonyball"],
					"started":[],
					"complete":[],
					"remark":"",
					"number_of_question":"",
					"answer_of_question":[]
				},
				{
					"id":"75",
					"title":"สับเซต",
					"course_id":"1",
					"course_code":"XTZ5218",
					"duration":"",
					"content_url":"9.mp4",
					"type":"video",
					"slide":"",
					"logo":"fa-film",
					"not_start":["tonyball"],
					"started":[],
					"complete":[],
					"remark":"",
					"number_of_question":"",
					"answer_of_question":[]
				},
				{
					"id":"76",
					"title":"โจทยที่ 7",
					"course_id":"1",
					"course_code":"XTZ5218",
					"duration":"",
					"type":"practice",
					"extended_remark":"",
					"answer_type":"multiple",
					"caption":["1","2","3","4"],
					"logo":"fa-pencil-square-o",
					"content_url":"7.png",
					"not_start":["tonyball"],
					"started":[],
					"complete":[],
					"remark":"เลือกข้อที่ถูกต้องที่สุด",
					"number_of_question":1,
					"answer_of_question":["3"]
				},
				{
					"id":"77",
					"title":"เฉลย โจทย์ที่ 7 ",
					"course_id":"1",
					"course_code":"XTZ5218",
					"duration":"",
					"content_url":"10.mp4",
					"type":"video",
					"slide":"",
					"logo":"fa-film",
					"not_start":["tonyball"],
					"started":[],
					"complete":[],
					"remark":"",
					"number_of_question":"",
					"answer_of_question":[]
				},
				{
					"id":"78",
					"title":"โจทยที่ 8",
					"course_id":"1",
					"course_code":"XTZ5218",
					"duration":"",
					"type":"practice",
					"extended_remark":"",
					"answer_type":"multiple",
					"caption":["1","2","3","4"],
					"logo":"fa-pencil-square-o",
					"content_url":"11.png",
					"not_start":["tonyball"],
					"started":[],
					"complete":[],
					"remark":"เลือกข้อที่ถูกต้องที่สุด",
					"number_of_question":1,
					"answer_of_question":["1"]
				},
				{
					"id":"79",
					"title":"เฉลย โจทย์ที่ 8 ",
					"course_id":"1",
					"course_code":"XTZ5218",
					"duration":"",
					"content_url":"11.mp4",
					"type":"video",
					"slide":"",
					"logo":"fa-film",
					"not_start":["tonyball"],
					"started":[],
					"complete":[],
					"remark":"",
					"number_of_question":"",
					"answer_of_question":[]
				},
				{
					"id":"80",
					"title":"โจทยที่ 9",
					"course_id":"1",
					"course_code":"XTZ5218",
					"duration":"",
					"type":"practice",
					"extended_remark":"",
					"answer_type":"multiple",
					"caption":["1","2","3","4"],
					"logo":"fa-pencil-square-o",
					"content_url":"9.png",
					"not_start":["tonyball"],
					"started":[],
					"complete":[],
					"remark":"เลือกข้อที่ถูกต้องที่สุด",
					"number_of_question":1,
					"answer_of_question":["3"]
				},
				{
					"id":"81",
					"title":"เฉลย โจทย์ที่ 9 ",
					"course_id":"1",
					"course_code":"XTZ5218",
					"duration":"",
					"content_url":"12.mp4",
					"type":"video",
					"slide":"",
					"logo":"fa-film",
					"not_start":["tonyball"],
					"started":[],
					"complete":[],
					"remark":"",
					"number_of_question":"",
					"answer_of_question":[]
				},
				{
					"id":"82",
					"title":"โจทยที่ 10",
					"course_id":"1",
					"course_code":"XTZ5218",
					"duration":"",
					"type":"practice",
					"extended_remark":"",
					"answer_type":"multiple",
					"caption":["1","2","3","4"],
					"logo":"fa-pencil-square-o",
					"content_url":"10.png",
					"not_start":["tonyball"],
					"started":[],
					"complete":[],
					"remark":"เลือกข้อที่ถูกต้องที่สุด",
					"number_of_question":1,
					"answer_of_question":["4"]
				},
				{
					"id":"83",
					"title":"เฉลย โจทย์ที่ 10 ",
					"course_id":"1",
					"course_code":"XTZ5218",
					"duration":"",
					"content_url":"13.mp4",
					"type":"video",
					"slide":"",
					"logo":"fa-film",
					"not_start":["tonyball"],
					"started":[],
					"complete":[],
					"remark":"",
					"number_of_question":"",
					"answer_of_question":[]
				},
				{
					"id":"84",
					"title":"โจทยที่ 11",
					"course_id":"1",
					"course_code":"XTZ5218",
					"duration":"",
					"type":"practice",
					"extended_remark":"",
					"answer_type":"multiple",
					"caption":["1","2","3","4"],
					"logo":"fa-pencil-square-o",
					"content_url":"11.png",
					"not_start":["tonyball"],
					"started":[],
					"complete":[],
					"remark":"เลือกข้อที่ถูกต้องที่สุด",
					"number_of_question":1,
					"answer_of_question":["3"]
				},
				{
					"id":"85",
					"title":"เฉลย โจทย์ที่ 11 ",
					"course_id":"1",
					"course_code":"XTZ5218",
					"duration":"",
					"content_url":"14.mp4",
					"type":"video",
					"slide":"",
					"logo":"fa-film",
					"not_start":["tonyball"],
					"started":[],
					"complete":[],
					"remark":"",
					"number_of_question":"",
					"answer_of_question":[]
				},
				{
					"id":"86",
					"title":"เพาเวอร์เซต ",
					"course_id":"1",
					"course_code":"XTZ5218",
					"duration":"",
					"content_url":"15.mp4",
					"type":"video",
					"slide":"",
					"logo":"fa-film",
					"not_start":["tonyball"],
					"started":[],
					"complete":[],
					"remark":"",
					"number_of_question":"",
					"answer_of_question":[]
				},
				{
					"id":"87",
					"title":"โจทยที่ 12",
					"course_id":"1",
					"course_code":"XTZ5218",
					"duration":"",
					"type":"practice",
					"extended_remark":"",
					"answer_type":"text",
					"caption":"",
					"logo":"fa-pencil-square-o",
					"content_url":"12.png",
					"not_start":["tonyball"],
					"started":[],
					"complete":[],
					"remark":"ให้ตอบเป็นรูปแบบพาวเวอร์เซต Ex P(A) = {1,2,3}",
					"number_of_question":2,
					"answer_of_question":["P(A)={{a},{b},{a,b},{∅}}","P(B)={{1},{2},{3},{1,2},{1,3},{2,3},{1,2,3},{∅}}"]
				},
				{
					"id":"88",
					"title":"เฉลย โจทย์ที่ 12 ",
					"course_id":"1",
					"course_code":"XTZ5218",
					"duration":"",
					"content_url":"16.mp4",
					"type":"video",
					"slide":"",
					"logo":"fa-film",
					"not_start":["tonyball"],
					"started":[],
					"complete":[],
					"remark":"",
					"number_of_question":"",
					"answer_of_question":[]
				},
				{
					"id":"89",
					"title":"โจทยที่ 13",
					"course_id":"1",
					"course_code":"XTZ5218",
					"duration":"",
					"type":"practice",
					"extended_remark":"",
					"answer_type":"multiple",
					"caption":["1","2","3","4"],
					"logo":"fa-pencil-square-o",
					"content_url":"13.png",
					"not_start":["tonyball"],
					"started":[],
					"complete":[],
					"remark":"เลือกข้อที่ถูกต้องที่สุด",
					"number_of_question":1,
					"answer_of_question":["4"]
				},
				{
					"id":"90",
					"title":"เฉลย โจทย์ที่ 13 ",
					"course_id":"1",
					"course_code":"XTZ5218",
					"duration":"",
					"content_url":"17.mp4",
					"type":"video",
					"slide":"",
					"logo":"fa-film",
					"not_start":["tonyball"],
					"started":[],
					"complete":[],
					"remark":"",
					"number_of_question":"",
					"answer_of_question":[]
				},
				{
					"id":"91",
					"title":"โจทยที่ 14",
					"course_id":"1",
					"course_code":"XTZ5218",
					"duration":"",
					"type":"practice",
					"extended_remark":"",
					"answer_type":"multiple",
					"caption":["1","2","3","4"],
					"logo":"fa-pencil-square-o",
					"content_url":"14.png",
					"not_start":["tonyball"],
					"started":[],
					"complete":[],
					"remark":"เลือกข้อที่ถูกต้องที่สุด",
					"number_of_question":1,
					"answer_of_question":["4"]
				},
				{
					"id":"92",
					"title":"เฉลย โจทย์ที่ 14 ",
					"course_id":"1",
					"course_code":"XTZ5218",
					"duration":"",
					"content_url":"18.mp4",
					"type":"video",
					"slide":"",
					"logo":"fa-film",
					"not_start":["tonyball"],
					"started":[],
					"complete":[],
					"remark":"",
					"number_of_question":"",
					"answer_of_question":[]
				},
				{
					"id":"93",
					"title":"โจทยที่ 15",
					"course_id":"1",
					"course_code":"XTZ5218",
					"duration":"",
					"type":"practice",
					"extended_remark":"",
					"answer_type":"multiple",
					"caption":["1","2","3","4"],
					"logo":"fa-pencil-square-o",
					"content_url":"15.png",
					"not_start":["tonyball"],
					"started":[],
					"complete":[],
					"remark":"เลือกข้อที่ถูกต้องที่สุด",
					"number_of_question":1,
					"answer_of_question":["3"]
				},
				{
					"id":"94",
					"title":"เฉลย โจทย์ที่ 15 ",
					"course_id":"1",
					"course_code":"XTZ5218",
					"duration":"",
					"content_url":"19.mp4",
					"type":"video",
					"slide":"",
					"logo":"fa-film",
					"not_start":["tonyball"],
					"started":[],
					"complete":[],
					"remark":"",
					"number_of_question":"",
					"answer_of_question":[]
				},
				{
					"id":"95",
					"title":"โจทยที่ 16",
					"course_id":"1",
					"course_code":"XTZ5218",
					"duration":"",
					"type":"practice",
					"extended_remark":"",
					"answer_type":"multiple",
					"caption":["1","2","3","4"],
					"logo":"fa-pencil-square-o",
					"content_url":"16.png",
					"not_start":["tonyball"],
					"started":[],
					"complete":[],
					"remark":"เลือกข้อที่ถูกต้องที่สุด",
					"number_of_question":1,
					"answer_of_question":["3"]
				},
				{
					"id":"96",
					"title":"เฉลย โจทย์ที่ 16 ",
					"course_id":"1",
					"course_code":"XTZ5218",
					"duration":"",
					"content_url":"20.mp4",
					"type":"video",
					"slide":"",
					"logo":"fa-film",
					"not_start":["tonyball"],
					"started":[],
					"complete":[],
					"remark":"",
					"number_of_question":"",
					"answer_of_question":[]
				},
				{
					"id":"97",
					"title":"โจทยที่ 17",
					"course_id":"1",
					"course_code":"XTZ5218",
					"duration":"",
					"type":"practice",
					"extended_remark":"",
					"answer_type":"multiple",
					"caption":["1","2","3","4"],
					"logo":"fa-pencil-square-o",
					"content_url":"17.png",
					"not_start":["tonyball"],
					"started":[],
					"complete":[],
					"remark":"เลือกข้อที่ถูกต้องที่สุด",
					"number_of_question":1,
					"answer_of_question":["3"]
				},
				{
					"id":"98",
					"title":"เฉลย โจทย์ที่ 17 ",
					"course_id":"1",
					"course_code":"XTZ5218",
					"duration":"",
					"content_url":"21.mp4",
					"type":"video",
					"slide":"",
					"logo":"fa-film",
					"not_start":["tonyball"],
					"started":[],
					"complete":[],
					"remark":"",
					"number_of_question":"",
					"answer_of_question":[]
				},
				{
					"id":"99",
					"title":"โจทยที่ 18",
					"course_id":"1",
					"course_code":"XTZ5218",
					"duration":"",
					"type":"practice",
					"extended_remark":"",
					"answer_type":"multiple",
					"caption":["1","2","3","4"],
					"logo":"fa-pencil-square-o",
					"content_url":"18.png",
					"not_start":["tonyball"],
					"started":[],
					"complete":[],
					"remark":"เลือกข้อที่ถูกต้องที่สุด",
					"number_of_question":1,
					"answer_of_question":["4"]
				},
				{
					"id":"100",
					"title":"เฉลย โจทย์ที่ 18 ",
					"course_id":"1",
					"course_code":"XTZ5218",
					"duration":"",
					"content_url":"22.mp4",
					"type":"video",
					"slide":"",
					"logo":"fa-film",
					"not_start":["tonyball"],
					"started":[],
					"complete":[],
					"remark":"ให้",
					"number_of_question":"",
					"answer_of_question":[]
				},
				{
					"id":"101",
					"title":"โจทยที่ 19",
					"course_id":"1",
					"course_code":"XTZ5218",
					"duration":"",
					"type":"practice",
					"extended_remark":"",
					"answer_type":"multiple",
					"caption":["1","2","3","4"],
					"logo":"fa-pencil-square-o",
					"content_url":"22.png",
					"not_start":["tonyball"],
					"started":[],
					"complete":[],
					"remark":"เลือกข้อที่ถูกต้องที่สุด",
					"number_of_question":1,
					"answer_of_question":["3"]
				},
				{
					"id":"102",
					"title":"เฉลย โจทย์ที่ 19 ",
					"course_id":"1",
					"course_code":"XTZ5218",
					"duration":"",
					"content_url":"23.mp4",
					"type":"video",
					"slide":"",
					"logo":"fa-film",
					"not_start":["tonyball"],
					"started":[],
					"complete":[],
					"remark":"",
					"number_of_question":"",
					"answer_of_question":[]
				},
				{
					"id":"103",
					"title":"โจทยที่ 20",
					"course_id":"1",
					"course_code":"XTZ5218",
					"duration":"",
					"type":"practice",
					"extended_remark":"",
					"answer_type":"multiple",
					"caption":["1","2","3","4"],
					"logo":"fa-pencil-square-o",
					"content_url":"20.png",
					"not_start":["tonyball"],
					"started":[],
					"complete":[],
					"remark":"เลือกข้อที่ถูกต้องที่สุด",
					"number_of_question":1,
					"answer_of_question":["2"]
				},
				{
					"id":"104",
					"title":"เฉลย โจทย์ที่ 20 ",
					"course_id":"1",
					"course_code":"XTZ5218",
					"duration":"",
					"content_url":"24.mp4",
					"type":"video",
					"slide":"",
					"logo":"fa-film",
					"not_start":["tonyball"],
					"started":[],
					"complete":[],
					"remark":"",
					"number_of_question":"",
					"answer_of_question":[]
				},
				{
					"id":"105",
					"title":"โจทยที่ 21",
					"course_id":"1",
					"course_code":"XTZ5218",
					"duration":"",
					"type":"practice",
					"extended_remark":"",
					"answer_type":"multiple",
					"caption":["1","2","3","4"],
					"logo":"fa-pencil-square-o",
					"content_url":"21.png",
					"not_start":["tonyball"],
					"started":[],
					"complete":[],
					"remark":"เลือกข้อที่ถูกต้องที่สุด",
					"number_of_question":1,
					"answer_of_question":["3"]
				},
				{
					"id":"106",
					"title":"เฉลย โจทย์ที่ 21 ",
					"course_id":"1",
					"course_code":"XTZ5218",
					"duration":"",
					"content_url":"25.mp4",
					"type":"video",
					"slide":"",
					"logo":"fa-film",
					"not_start":["tonyball"],
					"started":[],
					"complete":[],
					"remark":"",
					"number_of_question":"",
					"answer_of_question":[]
				},
				{
					"id":"107",
					"title":"โจทยที่ 22",
					"course_id":"1",
					"course_code":"XTZ5218",
					"duration":"",
					"type":"practice",
					"extended_remark":"",
					"answer_type":"text",
					"caption":"",
					"logo":"fa-pencil-square-o",
					"content_url":"22.png",
					"not_start":["tonyball","chanon","chatinya","chirapatr","chutipa","itouchz","jareewan","kantaporn","keeranat","kritawat","kritsada","kunlapat","natdecha","natthanon","thanwarat"],
					"started":[],
					"complete":[],
					"remark":"ให้ตอบเป็นตัวเลข",
					"number_of_question":1,
					"answer_of_question":["128"]
				},
				{
					"id":"108",
					"title":"เฉลย โจทย์ที่ 22 ",
					"course_id":"1",
					"course_code":"XTZ5218",
					"duration":"",
					"content_url":"26.mp4",
					"type":"video",
					"slide":"",
					"logo":"fa-film",
					"not_start":["tonyball","chanon","chatinya","chirapatr","chutipa","itouchz","jareewan","kantaporn","keeranat","kritawat","kritsada","kunlapat","natdecha","natthanon","thanwarat"],
					"started":[],
					"complete":[],
					"remark":"",
					"number_of_question":"",
					"answer_of_question":[]
				},
				{
					"id":"109",
					"title":"Operation of Set ",
					"course_id":"1",
					"course_code":"XTZ5218",
					"duration":"",
					"content_url":"27.mp4",
					"type":"video",
					"slide":"",
					"logo":"fa-film",
					"not_start":["tonyball"],
					"started":[],
					"complete":[],
					"remark":"",
					"number_of_question":"",
					"answer_of_question":[]
				},
				{
					"id":"110",
					"title":"โจทยที่ 23",
					"course_id":"1",
					"course_code":"XTZ5218",
					"duration":"",
					"type":"practice",
					"extended_remark":"",
					"answer_type":"multiple",
					"caption":["1","2","3","4"],
					"logo":"fa-pencil-square-o",
					"content_url":"22.png",
					"not_start":["tonyball"],
					"started":[],
					"complete":[],
					"remark":"เลือกข้อที่ถูกต้องที่สุด",
					"number_of_question":1,
					"answer_of_question":["3"]
				},
				{
					"id":"111",
					"title":"เฉลย โจทย์ที่ 23 ",
					"course_id":"1",
					"course_code":"XTZ5218",
					"duration":"",
					"content_url":"28.mp4",
					"type":"video",
					"slide":"",
					"logo":"fa-film",
					"not_start":["tonyball"],
					"started":[],
					"complete":[],
					"remark":"",
					"number_of_question":"",
					"answer_of_question":[]
				},
				{
					"id":"112",
					"title":"โจทยที่ 24",
					"course_id":"1",
					"course_code":"XTZ5218",
					"duration":"",
					"type":"practice",
					"extended_remark":"",
					"answer_type":"multiple",
					"caption":["1","2","3","4"],
					"logo":"fa-pencil-square-o",
					"content_url":"21.png",
					"not_start":["tonyball"],
					"started":[],
					"complete":[],
					"remark":"เลือกข้อที่ถูกต้องที่สุด",
					"number_of_question":1,
					"answer_of_question":["3"]
				},
				{
					"id":"113",
					"title":"เฉลย โจทย์ที่ 24 ",
					"course_id":"1",
					"course_code":"XTZ5218",
					"duration":"",
					"content_url":"29.mp4",
					"type":"video",
					"slide":"",
					"logo":"fa-film",
					"not_start":["tonyball"],
					"started":[],
					"complete":[],
					"remark":"",
					"number_of_question":"",
					"answer_of_question":[]
				},
				{
					"id":"114",
					"title":"โจทยที่ 25",
					"course_id":"1",
					"course_code":"XTZ5218",
					"duration":"",
					"type":"practice",
					"extended_remark":"",
					"answer_type":"multiple",
					"caption":["1","2","3","4"],
					"logo":"fa-pencil-square-o",
					"content_url":"21.png",
					"not_start":["tonyball"],
					"started":[],
					"complete":[],
					"remark":"เลือกข้อที่ถูกต้องที่สุด",
					"number_of_question":1,
					"answer_of_question":["3"]
				},
				{
					"id":"115",
					"title":"เฉลย โจทย์ที่ 25 ",
					"course_id":"1",
					"course_code":"XTZ5218",
					"duration":"",
					"content_url":"30.mp4",
					"type":"video",
					"slide":"",
					"logo":"fa-film",
					"not_start":["tonyball"],
					"started":[],
					"complete":[],
					"remark":"",
					"number_of_question":"",
					"answer_of_question":[]
				},
				{
					"id":"116",
					"title":"โจทยที่ 26",
					"course_id":"1",
					"course_code":"XTZ5218",
					"duration":"",
					"type":"practice",
					"extended_remark":"",
					"answer_type":"multiple",
					"caption":["1","2","3","4"],
					"logo":"fa-pencil-square-o",
					"content_url":"21.png",
					"not_start":["tonyball"],
					"started":[],
					"complete":[],
					"remark":"เลือกข้อที่ถูกต้องที่สุด",
					"number_of_question":1,
					"answer_of_question":["3"]
				},
				{
					"id":"117",
					"title":"เฉลย โจทย์ที่ 26 ",
					"course_id":"1",
					"course_code":"XTZ5218",
					"duration":"",
					"content_url":"31.mp4",
					"type":"video",
					"slide":"",
					"logo":"fa-film",
					"not_start":["tonyball"],
					"started":[],
					"complete":[],
					"remark":"",
					"number_of_question":"",
					"answer_of_question":[]
				},
				{
					"id":"118",
					"title":"โจทยที่ 27",
					"course_id":"1",
					"course_code":"XTZ5218",
					"duration":"",
					"type":"practice",
					"extended_remark":"",
					"answer_type":"multiple",
					"caption":["1","2","3","4"],
					"logo":"fa-pencil-square-o",
					"content_url":"21.png",
					"not_start":["tonyball"],
					"started":[],
					"complete":[],
					"remark":"เลือกข้อที่ถูกต้องที่สุด",
					"number_of_question":1,
					"answer_of_question":["3"]
				},
				{
					"id":"119",
					"title":"เฉลย โจทย์ที่ 27 ",
					"course_id":"1",
					"course_code":"XTZ5218",
					"duration":"",
					"content_url":"32.mp4",
					"type":"video",
					"slide":"",
					"logo":"fa-film",
					"not_start":["tonyball"],
					"started":[],
					"complete":[],
					"remark":"",
					"number_of_question":"",
					"answer_of_question":[]
				},
				{
					"id":"120",
					"title":"โจทยที่ 28",
					"course_id":"1",
					"course_code":"XTZ5218",
					"duration":"",
					"type":"practice",
					"extended_remark":"",
					"answer_type":"multiple",
					"caption":["1","2","3","4"],
					"logo":"fa-pencil-square-o",
					"content_url":"21.png",
					"not_start":["tonyball"],
					"started":[],
					"complete":[],
					"remark":"เลือกข้อที่ถูกต้องที่สุด",
					"number_of_question":1,
					"answer_of_question":["3"]
				},
				{
					"id":"121",
					"title":"เฉลย โจทย์ที่ 28 ",
					"course_id":"1",
					"course_code":"XTZ5218",
					"duration":"",
					"content_url":"33.mp4",
					"type":"video",
					"slide":"",
					"logo":"fa-film",
					"not_start":["tonyball"],
					"started":[],
					"complete":[],
					"remark":"",
					"number_of_question":"",
					"answer_of_question":[]
				},
				{
					"id":"122",
					"title":"โจทยที่ 29",
					"course_id":"1",
					"course_code":"XTZ5218",
					"duration":"",
					"type":"practice",
					"extended_remark":"",
					"answer_type":"multiple",
					"caption":["1","2","3","4"],
					"logo":"fa-pencil-square-o",
					"content_url":"21.png",
					"not_start":["tonyball"],
					"started":[],
					"complete":[],
					"remark":"เลือกข้อที่ถูกต้องที่สุด",
					"number_of_question":1,
					"answer_of_question":["3"]
				},
				{
					"id":"123",
					"title":"เฉลย โจทย์ที่ 29 ",
					"course_id":"1",
					"course_code":"XTZ5218",
					"duration":"",
					"content_url":"34.mp4",
					"type":"video",
					"slide":"",
					"logo":"fa-film",
					"not_start":["tonyball"],
					"started":[],
					"complete":[],
					"remark":"",
					"number_of_question":"",
					"answer_of_question":[]
				},
				{
					"id":"124",
					"title":"โจทยที่ 30",
					"course_id":"1",
					"course_code":"XTZ5218",
					"duration":"",
					"type":"practice",
					"extended_remark":"",
					"answer_type":"multiple",
					"caption":["1","2","3","4"],
					"logo":"fa-pencil-square-o",
					"content_url":"21.png",
					"not_start":["tonyball"],
					"started":[],
					"complete":[],
					"remark":"เลือกข้อที่ถูกต้องที่สุด",
					"number_of_question":1,
					"answer_of_question":["3"]
				},
				{
					"id":"125",
					"title":"เฉลย โจทย์ที่ 30 ",
					"course_id":"1",
					"course_code":"XTZ5218",
					"duration":"",
					"content_url":"35.mp4",
					"type":"video",
					"slide":"",
					"logo":"fa-film",
					"not_start":["tonyball"],
					"started":[],
					"complete":[],
					"remark":"",
					"number_of_question":"",
					"answer_of_question":[]
				},
				{
					"id":"126",
					"title":"โจทยที่ 31",
					"course_id":"1",
					"course_code":"XTZ5218",
					"duration":"",
					"type":"practice",
					"extended_remark":"",
					"answer_type":"multiple",
					"caption":["1","2","3","4"],
					"logo":"fa-pencil-square-o",
					"content_url":"21.png",
					"not_start":["tonyball"],
					"started":[],
					"complete":[],
					"remark":"เลือกข้อที่ถูกต้องที่สุด",
					"number_of_question":1,
					"answer_of_question":["3"]
				},
				{
					"id":"127",
					"title":"เฉลย โจทย์ที่ 31 ",
					"course_id":"1",
					"course_code":"XTZ5218",
					"duration":"",
					"content_url":"36.mp4",
					"type":"video",
					"slide":"",
					"logo":"fa-film",
					"not_start":["tonyball"],
					"started":[],
					"complete":[],
					"remark":"",
					"number_of_question":"",
					"answer_of_question":[]
				},
				{
					"id":"128",
					"title":"โจทยที่ 32",
					"course_id":"1",
					"course_code":"XTZ5218",
					"duration":"",
					"type":"practice",
					"extended_remark":"",
					"answer_type":"multiple",
					"caption":["1","2","3","4"],
					"logo":"fa-pencil-square-o",
					"content_url":"21.png",
					"not_start":["tonyball"],
					"started":[],
					"complete":[],
					"remark":"เลือกข้อที่ถูกต้องที่สุด",
					"number_of_question":1,
					"answer_of_question":["3"]
				},
				{
					"id":"129",
					"title":"เฉลย โจทย์ที่ 33 ",
					"course_id":"1",
					"course_code":"XTZ5218",
					"duration":"",
					"content_url":"37.mp4",
					"type":"video",
					"slide":"",
					"logo":"fa-film",
					"not_start":["tonyball"],
					"started":[],
					"complete":[],
					"remark":"",
					"number_of_question":"",
					"answer_of_question":[]
				},
				{
					"id":"130",
					"title":"โจทยที่ 34",
					"course_id":"1",
					"course_code":"XTZ5218",
					"duration":"",
					"type":"practice",
					"extended_remark":"",
					"answer_type":"multiple",
					"caption":["1","2","3","4"],
					"logo":"fa-pencil-square-o",
					"content_url":"21.png",
					"not_start":["tonyball"],
					"started":[],
					"complete":[],
					"remark":"เลือกข้อที่ถูกต้องที่สุด",
					"number_of_question":1,
					"answer_of_question":["3"]
				},
				{
					"id":"131",
					"title":"เฉลย โจทย์ที่ 34 ",
					"course_id":"1",
					"course_code":"XTZ5218",
					"duration":"",
					"content_url":"38.mp4",
					"type":"video",
					"slide":"",
					"logo":"fa-film",
					"not_start":["tonyball"],
					"started":[],
					"complete":[],
					"remark":"",
					"number_of_question":"",
					"answer_of_question":[]
				},
				{
					"id":"132",
					"title":"โจทยที่ 35",
					"course_id":"1",
					"course_code":"XTZ5218",
					"duration":"",
					"type":"practice",
					"extended_remark":"",
					"answer_type":"multiple",
					"caption":["1","2","3","4"],
					"logo":"fa-pencil-square-o",
					"content_url":"21.png",
					"not_start":["tonyball"],
					"started":[],
					"complete":[],
					"remark":"เลือกข้อที่ถูกต้องที่สุด",
					"number_of_question":1,
					"answer_of_question":["3"]
				},
				{
					"id":"133",
					"title":"เฉลย โจทย์ที่ 35 ",
					"course_id":"1",
					"course_code":"XTZ5218",
					"duration":"",
					"content_url":"39.mp4",
					"type":"video",
					"slide":"",
					"logo":"fa-film",
					"not_start":["tonyball"],
					"started":[],
					"complete":[],
					"remark":"",
					"number_of_question":"",
					"answer_of_question":[]
				},
				{
					"id":"134",
					"title":"โจทยที่ 36",
					"course_id":"1",
					"course_code":"XTZ5218",
					"duration":"",
					"type":"practice",
					"extended_remark":"",
					"answer_type":"multiple",
					"caption":["1","2","3","4"],
					"logo":"fa-pencil-square-o",
					"content_url":"21.png",
					"not_start":["tonyball"],
					"started":[],
					"complete":[],
					"remark":"เลือกข้อที่ถูกต้องที่สุด",
					"number_of_question":1,
					"answer_of_question":["3"]
				},
				{
					"id":"135",
					"title":"เฉลย โจทย์ที่ 36 ",
					"course_id":"1",
					"course_code":"XTZ5218",
					"duration":"",
					"content_url":"40.mp4",
					"type":"video",
					"slide":"",
					"logo":"fa-film",
					"not_start":["tonyball"],
					"started":[],
					"complete":[],
					"remark":"",
					"number_of_question":"",
					"answer_of_question":[]
				},
				{
					"id":"136",
					"title":"โจทยที่ 37",
					"course_id":"1",
					"course_code":"XTZ5218",
					"duration":"",
					"type":"practice",
					"extended_remark":"",
					"answer_type":"multiple",
					"caption":["1","2","3","4"],
					"logo":"fa-pencil-square-o",
					"content_url":"21.png",
					"not_start":["tonyball"],
					"started":[],
					"complete":[],
					"remark":"เลือกข้อที่ถูกต้องที่สุด",
					"number_of_question":1,
					"answer_of_question":["3"]
				},
				{
					"id":"137",
					"title":"เฉลย โจทย์ที่ 37",
					"course_id":"1",
					"course_code":"XTZ5218",
					"duration":"",
					"content_url":"41.mp4",
					"type":"video",
					"slide":"",
					"logo":"fa-film",
					"not_start":["tonyball"],
					"started":[],
					"complete":[],
					"remark":"",
					"number_of_question":"",
					"answer_of_question":[]
				},
				{
					"id":"138",
					"title":"คุณสมบัติของพาวเวอร์เซต",
					"course_id":"1",
					"course_code":"XTZ5218",
					"duration":"",
					"content_url":"42.mp4",
					"type":"video",
					"slide":"",
					"logo":"fa-film",
					"not_start":["tonyball"],
					"started":[],
					"complete":[],
					"remark":"",
					"number_of_question":"",
					"answer_of_question":[]
				},
				{
					"id":"139",
					"title":"โจทยที่ 38",
					"course_id":"1",
					"course_code":"XTZ5218",
					"duration":"",
					"type":"practice",
					"extended_remark":"",
					"answer_type":"multiple",
					"caption":["1","2","3","4"],
					"logo":"fa-pencil-square-o",
					"content_url":"21.png",
					"not_start":["tonyball"],
					"started":[],
					"complete":[],
					"remark":"เลือกข้อที่ถูกต้องที่สุด",
					"number_of_question":1,
					"answer_of_question":["3"]
				},
				{
					"id":"140",
					"title":"เฉลย โจทย์ที่ 38 ",
					"course_id":"1",
					"course_code":"XTZ5218",
					"duration":"",
					"content_url":"43.mp4",
					"type":"video",
					"slide":"",
					"logo":"fa-film",
					"not_start":["tonyball"],
					"started":[],
					"complete":[],
					"remark":"",
					"number_of_question":"",
					"answer_of_question":[]
				},
				{
					"id":"141",
					"title":"โจทยที่ 39",
					"course_id":"1",
					"course_code":"XTZ5218",
					"duration":"",
					"type":"practice",
					"extended_remark":"",
					"answer_type":"multiple",
					"caption":["1","2","3","4"],
					"logo":"fa-pencil-square-o",
					"content_url":"21.png",
					"not_start":["tonyball"],
					"started":[],
					"complete":[],
					"remark":"เลือกข้อที่ถูกต้องที่สุด",
					"number_of_question":1,
					"answer_of_question":["3"]
				},
				{
					"id":"142",
					"title":"เฉลย โจทย์ที่ 39 ",
					"course_id":"1",
					"course_code":"XTZ5218",
					"duration":"",
					"content_url":"44.mp4",
					"type":"video",
					"slide":"",
					"logo":"fa-film",
					"not_start":["tonyball"],
					"started":[],
					"complete":[],
					"remark":"",
					"number_of_question":"",
					"answer_of_question":[]
				},
				{
					"id":"143",
					"title":"โจทยที่ 40",
					"course_id":"1",
					"course_code":"XTZ5218",
					"duration":"",
					"type":"practice",
					"extended_remark":"",
					"answer_type":"multiple",
					"caption":["1","2","3","4"],
					"logo":"fa-pencil-square-o",
					"content_url":"21.png",
					"not_start":["tonyball"],
					"started":[],
					"complete":[],
					"remark":"เลือกข้อที่ถูกต้องที่สุด",
					"number_of_question":1,
					"answer_of_question":["3"]
				},
				{
					"id":"144",
					"title":"เฉลย โจทย์ที่ 40 ",
					"course_id":"1",
					"course_code":"XTZ5218",
					"duration":"",
					"content_url":"45.mp4",
					"type":"video",
					"slide":"",
					"logo":"fa-film",
					"not_start":["tonyball"],
					"started":[],
					"complete":[],
					"remark":"",
					"number_of_question":"",
					"answer_of_question":[]
				},
				{
					"id":"145",
					"title":"คุณสมบัติ Operation",
					"course_id":"1",
					"course_code":"XTZ5218",
					"duration":"",
					"content_url":"46.mp4",
					"type":"video",
					"slide":"",
					"logo":"fa-film",
					"not_start":["tonyball"],
					"started":[],
					"complete":[],
					"remark":"",
					"number_of_question":"",
					"answer_of_question":[]
				},
				{
					"id":"146",
					"title":"โจทยที่ 41",
					"course_id":"1",
					"course_code":"XTZ5218",
					"duration":"",
					"type":"practice",
					"extended_remark":"",
					"answer_type":"multiple",
					"caption":["1","2","3","4"],
					"logo":"fa-pencil-square-o",
					"content_url":"21.png",
					"not_start":["tonyball"],
					"started":[],
					"complete":[],
					"remark":"เลือกข้อที่ถูกต้องที่สุด",
					"number_of_question":1,
					"answer_of_question":["3"]
				},
				{
					"id":"147",
					"title":"เฉลย โจทย์ที่ 41 ",
					"course_id":"1",
					"course_code":"XTZ5218",
					"duration":"",
					"content_url":"47.mp4",
					"type":"video",
					"slide":"",
					"logo":"fa-film",
					"not_start":["tonyball"],
					"started":[],
					"complete":[],
					"remark":"",
					"number_of_question":"",
					"answer_of_question":[]
				},
				{
					"id":"148",
					"title":"โจทยที่ 42",
					"course_id":"1",
					"course_code":"XTZ5218",
					"duration":"",
					"type":"practice",
					"extended_remark":"",
					"answer_type":"multiple",
					"caption":["1","2","3","4"],
					"logo":"fa-pencil-square-o",
					"content_url":"21.png",
					"not_start":["tonyball"],
					"started":[],
					"complete":[],
					"remark":"เลือกข้อที่ถูกต้องที่สุด",
					"number_of_question":1,
					"answer_of_question":["3"]
				},
				{
					"id":"149",
					"title":"เฉลย โจทย์ที่ 42 ",
					"course_id":"1",
					"course_code":"XTZ5218",
					"duration":"",
					"content_url":"48.mp4",
					"type":"video",
					"slide":"",
					"logo":"fa-film",
					"not_start":["tonyball"],
					"started":[],
					"complete":[],
					"remark":"",
					"number_of_question":"",
					"answer_of_question":[]
				},
				{
					"id":"150",
					"title":"โจทยที่ 43",
					"course_id":"1",
					"course_code":"XTZ5218",
					"duration":"",
					"type":"practice",
					"extended_remark":"",
					"answer_type":"multiple",
					"caption":["1","2","3","4"],
					"logo":"fa-pencil-square-o",
					"content_url":"21.png",
					"not_start":["tonyball"],
					"started":[],
					"complete":[],
					"remark":"เลือกข้อที่ถูกต้องที่สุด",
					"number_of_question":1,
					"answer_of_question":["3"]
				},
				{
					"id":"151",
					"title":"เฉลย โจทย์ที่ 43 ",
					"course_id":"1",
					"course_code":"XTZ5218",
					"duration":"",
					"content_url":"49.mp4",
					"type":"video",
					"slide":"",
					"logo":"fa-film",
					"not_start":["tonyball"],
					"started":[],
					"complete":[],
					"remark":"",
					"number_of_question":"",
					"answer_of_question":[]
				},
				{
					"id":"152",
					"title":"โจทยที่ 44",
					"course_id":"1",
					"course_code":"XTZ5218",
					"duration":"",
					"type":"practice",
					"extended_remark":"",
					"answer_type":"multiple",
					"caption":["1","2","3","4"],
					"logo":"fa-pencil-square-o",
					"content_url":"21.png",
					"not_start":["tonyball"],
					"started":[],
					"complete":[],
					"remark":"เลือกข้อที่ถูกต้องที่สุด",
					"number_of_question":1,
					"answer_of_question":["3"]
				},
				{
					"id":"153",
					"title":"เฉลย โจทย์ที่ 44 ",
					"course_id":"1",
					"course_code":"XTZ5218",
					"duration":"",
					"content_url":"50.mp4",
					"type":"video",
					"slide":"",
					"logo":"fa-film",
					"not_start":["tonyball"],
					"started":[],
					"complete":[],
					"remark":"",
					"number_of_question":"",
					"answer_of_question":[]
				},
				{
					"id":"154",
					"title":"โจทยที่ 45",
					"course_id":"1",
					"course_code":"XTZ5218",
					"duration":"",
					"type":"practice",
					"extended_remark":"",
					"answer_type":"multiple",
					"caption":["1","2","3","4"],
					"logo":"fa-pencil-square-o",
					"content_url":"21.png",
					"not_start":["tonyball"],
					"started":[],
					"complete":[],
					"remark":"เลือกข้อที่ถูกต้องที่สุด",
					"number_of_question":1,
					"answer_of_question":["3"]
				},
				{
					"id":"155",
					"title":"เฉลย โจทย์ที่ 45 ",
					"course_id":"1",
					"course_code":"XTZ5218",
					"duration":"",
					"content_url":"51.mp4",
					"type":"video",
					"slide":"",
					"logo":"fa-film",
					"not_start":["tonyball"],
					"started":[],
					"complete":[],
					"remark":"",
					"number_of_question":"",
					"answer_of_question":[]
				},
				{
					"id":"156",
					"title":"โจทยที่ 46",
					"course_id":"1",
					"course_code":"XTZ5218",
					"duration":"",
					"type":"practice",
					"extended_remark":"",
					"answer_type":"multiple",
					"caption":["1","2","3","4"],
					"logo":"fa-pencil-square-o",
					"content_url":"21.png",
					"not_start":["tonyball"],
					"started":[],
					"complete":[],
					"remark":"เลือกข้อที่ถูกต้องที่สุด",
					"number_of_question":1,
					"answer_of_question":["3"]
				},
				{
					"id":"157",
					"title":"เฉลย โจทย์ที่ 46 ",
					"course_id":"1",
					"course_code":"XTZ5218",
					"duration":"",
					"content_url":"52.mp4",
					"type":"video",
					"slide":"",
					"logo":"fa-film",
					"not_start":["tonyball"],
					"started":[],
					"complete":[],
					"remark":"",
					"number_of_question":"",
					"answer_of_question":[]
				},
				{
					"id":"158",
					"title":"โจทยที่ 47",
					"course_id":"1",
					"course_code":"XTZ5218",
					"duration":"",
					"type":"practice",
					"extended_remark":"",
					"answer_type":"multiple",
					"caption":["1","2","3","4"],
					"logo":"fa-pencil-square-o",
					"content_url":"21.png",
					"not_start":["tonyball"],
					"started":[],
					"complete":[],
					"remark":"เลือกข้อที่ถูกต้องที่สุด",
					"number_of_question":1,
					"answer_of_question":["3"]
				},
				{
					"id":"159",
					"title":"เฉลย โจทย์ที่ 47 ",
					"course_id":"1",
					"course_code":"XTZ5218",
					"duration":"",
					"content_url":"53.mp4",
					"type":"video",
					"slide":"",
					"logo":"fa-film",
					"not_start":["tonyball"],
					"started":[],
					"complete":[],
					"remark":"",
					"number_of_question":"",
					"answer_of_question":[]
				},
				{
					"id":"160",
					"title":"โจทยที่ 48",
					"course_id":"1",
					"course_code":"XTZ5218",
					"duration":"",
					"type":"practice",
					"extended_remark":"",
					"answer_type":"multiple",
					"caption":["1","2","3","4"],
					"logo":"fa-pencil-square-o",
					"content_url":"21.png",
					"not_start":["tonyball"],
					"started":[],
					"complete":[],
					"remark":"เลือกข้อที่ถูกต้องที่สุด",
					"number_of_question":1,
					"answer_of_question":["3"]
				},
				{
					"id":"161",
					"title":"เฉลย โจทย์ที่ 48 ",
					"course_id":"1",
					"course_code":"XTZ5218",
					"duration":"",
					"content_url":"54.mp4",
					"type":"video",
					"slide":"",
					"logo":"fa-film",
					"not_start":["tonyball"],
					"started":[],
					"complete":[],
					"remark":"",
					"number_of_question":"",
					"answer_of_question":[]
				},
				{
					"id":"162",
					"title":"โจทยที่ 49",
					"course_id":"1",
					"course_code":"XTZ5218",
					"duration":"",
					"type":"practice",
					"extended_remark":"",
					"answer_type":"multiple",
					"caption":["1","2","3","4"],
					"logo":"fa-pencil-square-o",
					"content_url":"21.png",
					"not_start":["tonyball"],
					"started":[],
					"complete":[],
					"remark":"เลือกข้อที่ถูกต้องที่สุด",
					"number_of_question":1,
					"answer_of_question":["3"]
				},
				{
					"id":"162",
					"title":"เฉลย โจทย์ที่ 49 ",
					"course_id":"1",
					"course_code":"XTZ5218",
					"duration":"",
					"content_url":"55.mp4",
					"type":"video",
					"slide":"",
					"logo":"fa-film",
					"not_start":["tonyball"],
					"started":[],
					"complete":[],
					"remark":"",
					"number_of_question":"",
					"answer_of_question":[]
				},
				{
					"id":"163",
					"title":"การหาจำนวนสมาชิก",
					"course_id":"1",
					"course_code":"XTZ5218",
					"duration":"",
					"content_url":"56.mp4",
					"type":"video",
					"slide":"",
					"logo":"fa-film",
					"not_start":["tonyball"],
					"started":[],
					"complete":[],
					"remark":"",
					"number_of_question":"",
					"answer_of_question":[]
				},
				{
					"id":"164",
					"title":"โจทยที่ 50",
					"course_id":"1",
					"course_code":"XTZ5218",
					"duration":"",
					"type":"practice",
					"extended_remark":"",
					"answer_type":"multiple",
					"caption":["1","2","3","4"],
					"logo":"fa-pencil-square-o",
					"content_url":"21.png",
					"not_start":["tonyball"],
					"started":[],
					"complete":[],
					"remark":"เลือกข้อที่ถูกต้องที่สุด",
					"number_of_question":1,
					"answer_of_question":["3"]
				},
				{
					"id":"165",
					"title":"เฉลย โจทย์ที่ 50 ",
					"course_id":"1",
					"course_code":"XTZ5218",
					"duration":"",
					"content_url":"57.mp4",
					"type":"video",
					"slide":"",
					"logo":"fa-film",
					"not_start":["tonyball"],
					"started":[],
					"complete":[],
					"remark":"",
					"number_of_question":"",
					"answer_of_question":[]
				},
				{
					"id":"166",
					"title":"โจทยที่ 51",
					"course_id":"1",
					"course_code":"XTZ5218",
					"duration":"",
					"type":"practice",
					"extended_remark":"",
					"answer_type":"multiple",
					"caption":["1","2","3","4"],
					"logo":"fa-pencil-square-o",
					"content_url":"21.png",
					"not_start":["tonyball"],
					"started":[],
					"complete":[],
					"remark":"เลือกข้อที่ถูกต้องที่สุด",
					"number_of_question":1,
					"answer_of_question":["3"]
				},
				{
					"id":"167",
					"title":"เฉลย โจทย์ที่ 51 ",
					"course_id":"1",
					"course_code":"XTZ5218",
					"duration":"",
					"content_url":"58.mp4",
					"type":"video",
					"slide":"",
					"logo":"fa-film",
					"not_start":["tonyball"],
					"started":[],
					"complete":[],
					"remark":"",
					"number_of_question":"",
					"answer_of_question":[]
				},
				{
					"id":"168",
					"title":"โจทยที่ 52",
					"course_id":"1",
					"course_code":"XTZ5218",
					"duration":"",
					"type":"practice",
					"extended_remark":"",
					"answer_type":"multiple",
					"caption":["1","2","3","4"],
					"logo":"fa-pencil-square-o",
					"content_url":"21.png",
					"not_start":["tonyball"],
					"started":[],
					"complete":[],
					"remark":"เลือกข้อที่ถูกต้องที่สุด",
					"number_of_question":1,
					"answer_of_question":["3"]
				},
				{
					"id":"169",
					"title":"เฉลย โจทย์ที่ 52 ",
					"course_id":"1",
					"course_code":"XTZ5218",
					"duration":"",
					"content_url":"59.mp4",
					"type":"video",
					"slide":"",
					"logo":"fa-film",
					"not_start":["tonyball"],
					"started":[],
					"complete":[],
					"remark":"",
					"number_of_question":"",
					"answer_of_question":[]
				},
				{
					"id":"170",
					"title":"โจทยที่ 53",
					"course_id":"1",
					"course_code":"XTZ5218",
					"duration":"",
					"type":"practice",
					"extended_remark":"",
					"answer_type":"multiple",
					"caption":["1","2","3","4"],
					"logo":"fa-pencil-square-o",
					"content_url":"21.png",
					"not_start":["tonyball"],
					"started":[],
					"complete":[],
					"remark":"เลือกข้อที่ถูกต้องที่สุด",
					"number_of_question":1,
					"answer_of_question":["3"]
				},
				{
					"id":"171",
					"title":"เฉลย โจทย์ที่ 53 ",
					"course_id":"1",
					"course_code":"XTZ5218",
					"duration":"",
					"content_url":"60.mp4",
					"type":"video",
					"slide":"",
					"logo":"fa-film",
					"not_start":["tonyball"],
					"started":[],
					"complete":[],
					"remark":"",
					"number_of_question":"",
					"answer_of_question":[]
				},
				{
					"id":"172",
					"title":"โจทยที่ 54",
					"course_id":"1",
					"course_code":"XTZ5218",
					"duration":"",
					"type":"practice",
					"extended_remark":"",
					"answer_type":"multiple",
					"caption":["1","2","3","4"],
					"logo":"fa-pencil-square-o",
					"content_url":"21.png",
					"not_start":["tonyball"],
					"started":[],
					"complete":[],
					"remark":"เลือกข้อที่ถูกต้องที่สุด",
					"number_of_question":1,
					"answer_of_question":["3"]
				},
				{
					"id":"173",
					"title":"เฉลย โจทย์ที่ 54 ",
					"course_id":"1",
					"course_code":"XTZ5218",
					"duration":"",
					"content_url":"61.mp4",
					"type":"video",
					"slide":"",
					"logo":"fa-film",
					"not_start":["tonyball"],
					"started":[],
					"complete":[],
					"remark":"",
					"number_of_question":"",
					"answer_of_question":[]
				},
				{
					"id":"174",
					"title":"โจทยที่ 55",
					"course_id":"1",
					"course_code":"XTZ5218",
					"duration":"",
					"type":"practice",
					"extended_remark":"",
					"answer_type":"multiple",
					"caption":["1","2","3","4"],
					"logo":"fa-pencil-square-o",
					"content_url":"21.png",
					"not_start":["tonyball"],
					"started":[],
					"complete":[],
					"remark":"เลือกข้อที่ถูกต้องที่สุด",
					"number_of_question":1,
					"answer_of_question":["3"]
				},
				{
					"id":"175",
					"title":"เฉลย โจทย์ที่ 55 ",
					"course_id":"1",
					"course_code":"XTZ5218",
					"duration":"",
					"content_url":"62.mp4",
					"type":"video",
					"slide":"",
					"logo":"fa-film",
					"not_start":["tonyball"],
					"started":[],
					"complete":[],
					"remark":"",
					"number_of_question":"",
					"answer_of_question":[]
				},
				{
					"id":"176",
					"title":"โจทยที่ 56",
					"course_id":"1",
					"course_code":"XTZ5218",
					"duration":"",
					"type":"practice",
					"extended_remark":"",
					"answer_type":"multiple",
					"caption":["1","2","3","4"],
					"logo":"fa-pencil-square-o",
					"content_url":"21.png",
					"not_start":["tonyball"],
					"started":[],
					"complete":[],
					"remark":"เลือกข้อที่ถูกต้องที่สุด",
					"number_of_question":1,
					"answer_of_question":["3"]
				},
				{
					"id":"177",
					"title":"เฉลย โจทย์ที่ 56 ",
					"course_id":"1",
					"course_code":"XTZ5218",
					"duration":"",
					"content_url":"63.mp4",
					"type":"video",
					"slide":"",
					"logo":"fa-film",
					"not_start":["tonyball"],
					"started":[],
					"complete":[],
					"remark":"",
					"number_of_question":"",
					"answer_of_question":[]
				},
				{
					"id":"178",
					"title":"โจทยที่ 57",
					"course_id":"1",
					"course_code":"XTZ5218",
					"duration":"",
					"type":"practice",
					"extended_remark":"",
					"answer_type":"multiple",
					"caption":["1","2","3","4"],
					"logo":"fa-pencil-square-o",
					"content_url":"21.png",
					"not_start":["tonyball"],
					"started":[],
					"complete":[],
					"remark":"เลือกข้อที่ถูกต้องที่สุด",
					"number_of_question":1,
					"answer_of_question":["3"]
				},
				{
					"id":"179",
					"title":"เฉลย โจทย์ที่ 57 ",
					"course_id":"1",
					"course_code":"XTZ5218",
					"duration":"",
					"content_url":"64.mp4",
					"type":"video",
					"slide":"",
					"logo":"fa-film",
					"not_start":["tonyball"],
					"started":[],
					"complete":[],
					"remark":"",
					"number_of_question":"",
					"answer_of_question":[]
				},
				{
					"id":"180",
					"title":"โจทยที่ 58",
					"course_id":"1",
					"course_code":"XTZ5218",
					"duration":"",
					"type":"practice",
					"extended_remark":"",
					"answer_type":"multiple",
					"caption":["1","2","3","4"],
					"logo":"fa-pencil-square-o",
					"content_url":"21.png",
					"not_start":["tonyball"],
					"started":[],
					"complete":[],
					"remark":"เลือกข้อที่ถูกต้องที่สุด",
					"number_of_question":1,
					"answer_of_question":["3"]
				},
				{
					"id":"181",
					"title":"เฉลย โจทย์ที่ 58 ",
					"course_id":"1",
					"course_code":"XTZ5218",
					"duration":"",
					"content_url":"65.mp4",
					"type":"video",
					"slide":"",
					"logo":"fa-film",
					"not_start":["tonyball"],
					"started":[],
					"complete":[],
					"remark":"",
					"number_of_question":"",
					"answer_of_question":[]
				},
				{
					"id":"182",
					"title":"โจทยที่ 59",
					"course_id":"1",
					"course_code":"XTZ5218",
					"duration":"",
					"type":"practice",
					"extended_remark":"",
					"answer_type":"multiple",
					"caption":["1","2","3","4"],
					"logo":"fa-pencil-square-o",
					"content_url":"21.png",
					"not_start":["tonyball"],
					"started":[],
					"complete":[],
					"remark":"เลือกข้อที่ถูกต้องที่สุด",
					"number_of_question":1,
					"answer_of_question":["3"]
				},
				{
					"id":"183",
					"title":"เฉลย โจทย์ที่ 59 ",
					"course_id":"1",
					"course_code":"XTZ5218",
					"duration":"",
					"content_url":"66.mp4",
					"type":"video",
					"slide":"",
					"logo":"fa-film",
					"not_start":["tonyball"],
					"started":[],
					"complete":[],
					"remark":"",
					"number_of_question":"",
					"answer_of_question":[]
				},
				{
					"id":"184",
					"title":"โจทยที่ 60",
					"course_id":"1",
					"course_code":"XTZ5218",
					"duration":"",
					"type":"practice",
					"extended_remark":"",
					"answer_type":"multiple",
					"caption":["1","2","3","4"],
					"logo":"fa-pencil-square-o",
					"content_url":"21.png",
					"not_start":["tonyball"],
					"started":[],
					"complete":[],
					"remark":"เลือกข้อที่ถูกต้องที่สุด",
					"number_of_question":1,
					"answer_of_question":["3"]
				},
				{
					"id":"185",
					"title":"เฉลย โจทย์ที่ 60 ",
					"course_id":"1",
					"course_code":"XTZ5218",
					"duration":"",
					"content_url":"67.mp4",
					"type":"video",
					"slide":"",
					"logo":"fa-film",
					"not_start":["tonyball"],
					"started":[],
					"complete":[],
					"remark":"",
					"number_of_question":"",
					"answer_of_question":[]
				},
				{
					"id":"186",
					"title":"โจทยที่ 61",
					"course_id":"1",
					"course_code":"XTZ5218",
					"duration":"",
					"type":"practice",
					"extended_remark":"",
					"answer_type":"multiple",
					"caption":["1","2","3","4"],
					"logo":"fa-pencil-square-o",
					"content_url":"21.png",
					"not_start":["tonyball"],
					"started":[],
					"complete":[],
					"remark":"เลือกข้อที่ถูกต้องที่สุด",
					"number_of_question":1,
					"answer_of_question":["3"]
				},
				{
					"id":"187",
					"title":"เฉลย โจทย์ที่ 61 ",
					"course_id":"1",
					"course_code":"XTZ5218",
					"duration":"",
					"content_url":"68.mp4",
					"type":"video",
					"slide":"",
					"logo":"fa-film",
					"not_start":["tonyball"],
					"started":[],
					"complete":[],
					"remark":"",
					"number_of_question":"",
					"answer_of_question":[]
				},
				{
					"id":"188",
					"title":"โจทยที่ 62",
					"course_id":"1",
					"course_code":"XTZ5218",
					"duration":"",
					"type":"practice",
					"extended_remark":"",
					"answer_type":"multiple",
					"caption":["1","2","3","4"],
					"logo":"fa-pencil-square-o",
					"content_url":"21.png",
					"not_start":["tonyball"],
					"started":[],
					"complete":[],
					"remark":"เลือกข้อที่ถูกต้องที่สุด",
					"number_of_question":1,
					"answer_of_question":["3"]
				},
				{
					"id":"189",
					"title":"เฉลย โจทย์ที่ 62 ",
					"course_id":"1",
					"course_code":"XTZ5218",
					"duration":"",
					"content_url":"69.mp4",
					"type":"video",
					"slide":"",
					"logo":"fa-film",
					"not_start":["tonyball"],
					"started":[],
					"complete":[],
					"remark":"",
					"number_of_question":"",
					"answer_of_question":[]
				}
			]
		},
		{
			"name": "Simulation Test",
			"contents":
			[
				{
					"id":"62",
					"title":"แบบทดสอบ เซต",
					"number_of_test":4,
					"course_id":"1",
					"course_code":"XTZ5218",
					"duration":"",
					"content_url":"XTZ5218.pdf",
					"type":"test",
					"logo":"fa-file-pdf-o",
					"not_start":["tonyball"],
					"started":["chanon","chatinya","chirapatr"],
					"complete":["chutipa","itouchz","jareewan","kantaporn","keeranat","kritawat","kritsada","kunlapat","natdecha","natthanon","thanwarat"],
					"remark":"",
					"time":[60,60,60,60],
					"number_of_question":[27,21,19,18],
					"answer_of_question":[[1,2,3,1,4,4,4,3,1,3,2,3,2,2,2,3,3,1,2,2,1,3,4,4,3,3,4],[4,2,4,3,3,3,8,2,1,1,4,1,1,4,2,33,2,3,3,3,4],[1,3,3,2,4,4,1,3,2,1,3,2,3,3,2,3,4,3,3],[3,4,2,3,4,2,3,1,26,2,1,4,3,13,415,4,3,1]]
				}
			]
		}
	],
	"tags":["เซต", "คณิตศาสตร์"],
	"students":["chanon","chatinya","chirapatr","chutipa","itouchz","jareewan","kantaporn","keeranat","kritawat","kritsada","kunlapat","natdecha","natthanon","thanwarat","tonyball"]
}